sariFieldDefinitionsGenerator/__init__.py
sariFieldDefinitionsGenerator/generator.py
sariFieldDefinitionsGenerator/templates/inline.handlebars
sariFieldDefinitionsGenerator/templates/json.handlebars
sariFieldDefinitionsGenerator/templates/metaphacts.handlebars
sariFieldDefinitionsGenerator/templates/researchspace.handlebars
sariFieldDefinitionsGenerator/templates/universal.handlebars
sari_field_definitions_generator-0.2.19.dist-info/LICENSE
sari_field_definitions_generator-0.2.19.dist-info/METADATA
sari_field_definitions_generator-0.2.19.dist-info/WHEEL
sari_field_definitions_generator-0.2.19.dist-info/top_level.txt
sari_field_definitions_generator-0.2.19.dist-info/RECORD
