Metadata-Version: 2.1
Name: sari-field-definitions-generator
Version: 0.2.19
Summary: A generator for Field Definitions for ResearchSpace and Metaphacts
Home-page: https://github.com/swiss-art-research-net/sari-field-definitions-generator.git
Author: Florian Kräutli
Author-email: florian.kraeutli@uzh.ch
License: UNKNOWN
Platform: UNKNOWN
Classifier: Programming Language :: Python :: 3
Classifier: License :: OSI Approved :: MIT License
Classifier: Operating System :: OS Independent
Requires-Python: >=3.6
Requires-Dist: pybars3
Requires-Dist: PyYAML
